methodinfrascan/__init__.py
methodinfrascan/core/__init__.py
methodinfrascan/core/datetime_utils.py
methodinfrascan/core/pydantic_utilities.py
methodinfrascan/core/serialization.py
methodinfrascan/py.typed
methodinfrascan/resources/__init__.py
methodinfrascan/resources/common/__init__.py
methodinfrascan/resources/common/resources/__init__.py
methodinfrascan/resources/common/resources/wireless/__init__.py
methodinfrascan/resources/common/resources/wireless/authentication_method.py
methodinfrascan/resources/common/resources/wireless/channel_width.py
methodinfrascan/resources/common/resources/wireless/cipher_suite.py
methodinfrascan/resources/common/resources/wireless/encryption_protocol.py
methodinfrascan/resources/common/resources/wireless/frame_type.py
methodinfrascan/resources/common/resources/wireless/frequency_band.py
methodinfrascan/resources/common/resources/wireless/key_management_type.py
methodinfrascan/resources/common/resources/wireless/pmf_policy.py
methodinfrascan/resources/common/resources/wireless/wifi_generation.py
methodinfrascan/resources/common/resources/wireless/wpa_version.py
methodinfrascan/resources/connect/__init__.py
methodinfrascan/resources/connect/resources/__init__.py
methodinfrascan/resources/connect/resources/wap/__init__.py
methodinfrascan/resources/connect/resources/wap/association_status_code.py
methodinfrascan/resources/connect/resources/wap/connection_attempt.py
methodinfrascan/resources/connect/resources/wap/connection_outcome.py
methodinfrascan/resources/connect/resources/wap/connection_timing.py
methodinfrascan/resources/connect/resources/wap/deauth_reason_code.py
methodinfrascan/resources/connect/resources/wap/eap_method.py
methodinfrascan/resources/connect/resources/wap/handshake_progress.py
methodinfrascan/resources/connect/resources/wap/negotiated_security.py
methodinfrascan/resources/connect/resources/wap/original_network_state.py
methodinfrascan/resources/connect/resources/wap/platform_connectivity_result.py
methodinfrascan-0.0.6.dist-info/METADATA
methodinfrascan-0.0.6.dist-info/WHEEL
methodinfrascan-0.0.6.dist-info/RECORD
